<?xml version="1.0"?>
  <Plugin name="PeaksOverThreshold" type="operator" label="PeaksOverThreshold" version="1.0" enabled="true" mdspecificcode="false" engspecificcode="false" onlyengine="false" noengine="false" createExpression="true" exprInType="scalar" exprOutType="scalar">
    <Attribute name="PeaksOverThresholdAttributes" purpose="Attributes for PeaksOverThreshold operator" persistent="true" keyframe="true" exportAPI="" exportInclude="">
      <Enum name="AggregationType">
        ANNUAL
        SEASONAL
        MONTHLY
      </Enum>
      <Enum name="SeasonType">
        WINTER
        SPRING
        SUMMER
        FALL
      </Enum>
      <Enum name="MonthType">
        JAN
        FEB
        MAR
        APR
        MAY
        JUN
        JUL
        AUG
        SEP
        OCT
        NOV
        DEC
      </Enum>
      <Field name="aggregationType" label="Aggregation Type" type="enum" subtype="AggregationType">
        ANNUAL
      </Field>
      <Field name="annualPercentile" label="Annual Percentile" type="double" enabler="aggregationType:ANNUAL">
        0.900000
      </Field>
      <Field name="seasonalPercentile" label="Seasonal Percentile" type="doubleArray" length="4" enabler="aggregationType:SEASONAL">
        0.900000
        0.900000
        0.900000
        0.900000
      </Field>
      <Field name="monthlyPercentile" label="Monthly Percentile" type="doubleArray" length="12" enabler="aggregationType:MONTHLY">
        0.900000
        0.900000
        0.900000
        0.900000
        0.900000
        0.900000
        0.900000
        0.900000
        0.900000
        0.900000
        0.900000
        0.900000
      </Field>
      <Field name="season" label="Display Season" type="enum" subtype="SeasonType" enabler="aggregationType:SEASONAL">
        WINTER
      </Field>
      <Field name="month" label="Display Month" type="enum" subtype="MonthType" enabler="aggregationType:MONTHLY">
        JAN
      </Field>
      <Field name="dataScaling" label="Data Scaling" type="double">
        86500.000000
      </Field>
      <Field name="dumpData" label="Dump Data" type="bool">
        false
      </Field>
    </Attribute>
  </Plugin>
